odoo/addons/mrp_workorder_blocking_time/README.rst
odoo/addons/mrp_workorder_blocking_time/__init__.py
odoo/addons/mrp_workorder_blocking_time/__manifest__.py
odoo/addons/mrp_workorder_blocking_time/i18n/it.po
odoo/addons/mrp_workorder_blocking_time/i18n/mrp_workorder_blocking_time.pot
odoo/addons/mrp_workorder_blocking_time/models/__init__.py
odoo/addons/mrp_workorder_blocking_time/models/mrp_routing_workcenter.py
odoo/addons/mrp_workorder_blocking_time/models/mrp_workorder.py
odoo/addons/mrp_workorder_blocking_time/readme/CONTRIBUTORS.md
odoo/addons/mrp_workorder_blocking_time/readme/DESCRIPTION.md
odoo/addons/mrp_workorder_blocking_time/readme/USAGE.md
odoo/addons/mrp_workorder_blocking_time/security/ir.model.access.csv
odoo/addons/mrp_workorder_blocking_time/static/description/icon.png
odoo/addons/mrp_workorder_blocking_time/static/description/index.html
odoo/addons/mrp_workorder_blocking_time/tests/__init__.py
odoo/addons/mrp_workorder_blocking_time/tests/test_mrp_workorder_blocking_time.py
odoo/addons/mrp_workorder_blocking_time/views/mrp_routing_workcenter.xml
odoo/addons/mrp_workorder_blocking_time/views/mrp_workorder.xml
odoo/addons/mrp_workorder_blocking_time/wizards/__init__.py
odoo/addons/mrp_workorder_blocking_time/wizards/wizard_open_blocking_popup.py
odoo/addons/mrp_workorder_blocking_time/wizards/wizard_open_blocking_popup.xml
odoo_addon_mrp_workorder_blocking_time-18.0.1.0.0.4.dist-info/METADATA
odoo_addon_mrp_workorder_blocking_time-18.0.1.0.0.4.dist-info/WHEEL
odoo_addon_mrp_workorder_blocking_time-18.0.1.0.0.4.dist-info/top_level.txt
odoo_addon_mrp_workorder_blocking_time-18.0.1.0.0.4.dist-info/RECORD
